{"trial_id": "5d3d7ccf1e81b0c69bb7020b1e78680b", "hyperparameters": {"space": [{"class_name": "Int", "config": {"name": "units_1", "default": null, "conditions": [], "min_value": 32, "max_value": 256, "step": 16, "sampling": null}}, {"class_name": "Int", "config": {"name": "units_2", "default": null, "conditions": [], "min_value": 32, "max_value": 256, "step": 16, "sampling": null}}, {"class_name": "Int", "config": {"name": "units_3", "default": null, "conditions": [], "min_value": 32, "max_value": 256, "step": 16, "sampling": null}}, {"class_name": "Int", "config": {"name": "units_4", "default": null, "conditions": [], "min_value": 32, "max_value": 256, "step": 16, "sampling": null}}, {"class_name": "Choice", "config": {"name": "learning_rate", "default": 0.01, "conditions": [], "values": [0.01, 0.001, 0.0001], "ordered": true}}], "values": {"units_1": 144, "units_2": 48, "units_3": 192, "units_4": 256, "learning_rate": 0.01, "tuner/epochs": 5, "tuner/initial_epoch": 2, "tuner/bracket": 2, "tuner/round": 1, "tuner/trial_id": "28cb3e731f17b22cd0a336306b133368"}}, "metrics": {"metrics": {"loss": {"direction": "min", "observations": [{"value": [191593.171875], "step": 0}]}, "mean_absolute_error": {"direction": "min", "observations": [{"value": [344.1096496582031], "step": 0}]}, "val_loss": {"direction": "min", "observations": [{"value": [180818.859375], "step": 0}]}, "val_mean_absolute_error": {"direction": "min", "observations": [{"value": [340.3585205078125], "step": 0}]}}}, "score": 340.3585205078125, "best_step": 0, "status": "COMPLETED"}